autorest/__init__.py
autorest/apps.py
autorest/permissions.py
autorest/sample_user_viewset.py
autorest/settings.py
autorest/tests.py
autorest/urls.py
autorest/wsgi.py
autorest/api/__init__.py
autorest/api/url_inflect.py
autorest/api/urls.py
autorest/api/views.py
django_autorest-1.0.1.dist-info/LICENSE
django_autorest-1.0.1.dist-info/METADATA
django_autorest-1.0.1.dist-info/WHEEL
django_autorest-1.0.1.dist-info/top_level.txt
django_autorest-1.0.1.dist-info/RECORD
