Metadata-Version: 2.1
Name: django-autorest
Version: 1.0.1
Summary: A re-useable Django app for automatically building a REST API based on models.
Home-page: https://github.com/gregschmit/django-autorest
Author: Gregory N. Schmit
Author-email: gschmi4@uic.edu
License: MIT
Platform: UNKNOWN
Classifier: Environment :: Web Environment
Classifier: Framework :: Django
Classifier: Intended Audience :: Developers
Classifier: License :: OSI Approved :: MIT License
Classifier: Programming Language :: Python :: 3
Requires-Dist: Django (>=2)
Requires-Dist: djangorestframework (>=3)
Requires-Dist: drf-action-serializer
Requires-Dist: inflection
